main.py
mcp_weather_buding6666-0.2.0.dist-info/METADATA
mcp_weather_buding6666-0.2.0.dist-info/WHEEL
mcp_weather_buding6666-0.2.0.dist-info/entry_points.txt
mcp_weather_buding6666-0.2.0.dist-info/top_level.txt
mcp_weather_buding6666-0.2.0.dist-info/RECORD
