Metadata-Version: 2.4
Name: mcp-weather-buding6666
Version: 0.2.0
Summary: 输入一个城市的名称，获取对应的前期情况
Requires-Python: >=3.11
Requires-Dist: httpx>=0.28.1
Requires-Dist: mcp>=1.12.4
Requires-Dist: requests>=2.32.4
